jinja2html/__init__.py
jinja2html/__main__.py
jinja2html/build_context.py
jinja2html/utils.py
jinja2html/web_ui.py
jinja2html/website_manager.py
jinja2html-0.5.0.dist-info/LICENSE.md
jinja2html-0.5.0.dist-info/METADATA
jinja2html-0.5.0.dist-info/WHEEL
jinja2html-0.5.0.dist-info/entry_points.txt
jinja2html-0.5.0.dist-info/top_level.txt
jinja2html-0.5.0.dist-info/RECORD
