Metadata-Version: 2.1
Name: jinja2html
Version: 0.5.0
Summary: user-friendly generation of websites with jinja2 templates
Home-page: https://github.com/fastily/jinja2html
Author: Fastily
Author-email: fastily@users.noreply.github.com
Project-URL: Bug Tracker, https://github.com/fastily/jinja2html/issues
Classifier: Natural Language :: English
Classifier: Programming Language :: Python :: 3
Classifier: Programming Language :: Python :: 3.9
Classifier: License :: OSI Approved :: GNU General Public License v3 (GPLv3)
Classifier: Operating System :: OS Independent
Requires-Python: >=3.9
License-File: LICENSE.md
Requires-Dist: beautifulsoup4
Requires-Dist: Jinja2
Requires-Dist: lxml
Requires-Dist: rich
Requires-Dist: starlette
Requires-Dist: uvicorn[standard]
